AUTHORS
LICENSE
MANIFEST.in
README.rst
setup.py
django_mockups_ng.egg-info/PKG-INFO
django_mockups_ng.egg-info/SOURCES.txt
django_mockups_ng.egg-info/dependency_links.txt
django_mockups_ng.egg-info/not-zip-safe
django_mockups_ng.egg-info/top_level.txt
docs/Makefile
docs/conf.py
docs/contribute.rst
docs/index.rst
docs/installation.rst
docs/make.bat
docs/mockups.rst
docs/registry.rst
docs/usage.rst
docs/_theme/nature/theme.conf
docs/_theme/nature/static/nature.css_t
docs/_theme/nature/static/pygments.css
mockups/__init__.py
mockups/base.py
mockups/constraints.py
mockups/factory.py
mockups/generators.py
mockups/helpers.py
mockups/models.py
mockups/signals.py
mockups/contrib/__init__.py
mockups/contrib/auth.py
mockups/management/__init__.py
mockups/management/commands/__init__.py
mockups/management/commands/mockups.py
mockups/tests/__init__.py
mockups/tests/models.py
mockups/tests/runtests.py
mockups/tests/urls.py
mockups/tests/generator_test/__init__.py
mockups/tests/generator_test/models.py
mockups/tests/generator_test/tests.py
mockups/tests/media/emptyfiles/empty.txt
mockups/tests/media/emptyfiles/nofilextension
mockups/tests/media/textfiles/ispum.txt
mockups/tests/media/textfiles/lorem.txt
mockups/tests/mockups_test/__init__.py
mockups/tests/mockups_test/models.py
mockups/tests/mockups_test/tests.py
mockups/tests/sample_app/__init__.py
mockups/tests/sample_app/admin.py
mockups/tests/sample_app/models.py