Metadata-Version: 1.1
Name: django-mockups-ng
Version: 0.5.0
Summary: Provides tools to auto generate content.
Home-page: https://github.com/sorl/django-mockups
Author: ifanr
Author-email: ifanrx@ifanr.com
License: BSD
Platform: any
Classifier: Development Status :: 4 - Beta
Classifier: Environment :: Web Environment
Classifier: Framework :: Django
Classifier: Intended Audience :: Developers
Classifier: License :: OSI Approved :: BSD License
Classifier: Natural Language :: English
Classifier: Operating System :: OS Independent
Classifier: Programming Language :: Python
